bigquery_dry_run/__init__.py
bigquery_dry_run/app.py
bigquery_dry_run-0.3.1.dist-info/entry_points.txt
bigquery_dry_run-0.3.1.dist-info/WHEEL
bigquery_dry_run-0.3.1.dist-info/METADATA
bigquery_dry_run-0.3.1.dist-info/RECORD
