Metadata-Version: 2.1
Name: bigquery-dry-run
Version: 0.3.1
Summary: This package is used to perform a BigQuery dry run of all `.sql` files in a folder and its subfolders.
License: MIT
Keywords: bigquery
Author: Christo Olivier
Author-email: mail@christoolivier.com
Requires-Python: >=3.6,<3.10
Classifier: License :: OSI Approved :: MIT License
Classifier: Programming Language :: Python :: 3
Classifier: Programming Language :: Python :: 3.6
Classifier: Programming Language :: Python :: 3.7
Classifier: Programming Language :: Python :: 3.8
Classifier: Programming Language :: Python :: 3.9
Requires-Dist: google-cloud-bigquery (>=2.13.1,<3.0.0)
Requires-Dist: pytz (>=2021.1,<2022.0)
